CHANGES.txt
MANIFEST.in
README.md
setup.py
djinn_core/__init__.py
djinn_core/__init__.pyc
djinn_core/pluginstaticfilesfinder.py
djinn_core/pluginstaticfilesfinder.pyc
djinn_core/serve_static.py
djinn_core/skintemplateloader.py
djinn_core/skintemplateloader.pyc
djinn_core/urls.py
djinn_core/urls.pyc
djinn_core/utils.py
djinn_core/utils.pyc
djinn_core.egg-info/PKG-INFO
djinn_core.egg-info/SOURCES.txt
djinn_core.egg-info/dependency_links.txt
djinn_core.egg-info/entry_points.txt
djinn_core.egg-info/not-zip-safe
djinn_core.egg-info/requires.txt
djinn_core.egg-info/top_level.txt
djinn_core/.idea/djinn_core.iml
djinn_core/.idea/encodings.xml
djinn_core/.idea/misc.xml
djinn_core/.idea/modules.xml
djinn_core/.idea/vcs.xml
djinn_core/.idea/workspace.xml
djinn_core/.idea/scopes/scope_settings.xml
djinn_core/static/css/djinn_core.css
djinn_core/static/js/djinn_core.js
djinn_core/templates/djinn_core/admin.html
djinn_core/templates/djinn_core/snippets/css.html
djinn_core/templates/djinn_core/snippets/js.html
djinn_core/templatetags/__init__.py
djinn_core/templatetags/__init__.pyc
djinn_core/templatetags/djinn_core.py
djinn_core/templatetags/djinn_core.pyc
djinn_core/views/__init__.py
djinn_core/views/__init__.pyc
djinn_core/views/admin.py
djinn_core/views/admin.pyc