Metadata-Version: 1.1
Name: djinn-core
Version: 1.2.9
Summary: Djinn Intranet core
Home-page: https://github.com/PythonUnited/djinn_core
Author: PythonUnited
Author-email: info@pythonunited.com
License: beer-ware
Keywords: Djinn Django intranet
Platform: UNKNOWN
Classifier: Development Status :: 5 - Production/Stable
Classifier: Framework :: Django
Classifier: Intended Audience :: Developers
Classifier: License :: Freely Distributable
Classifier: Programming Language :: Python
Classifier: Topic :: Internet :: WWW/HTTP :: Site Management
Classifier: Topic :: Software Development :: Libraries :: Application Frameworks
